happybase.py
aiohappybase/Hbase.thrift
aiohappybase/__init__.py
aiohappybase/_load_hbase_thrift.py
aiohappybase/_util.py
aiohappybase/_version.py
aiohappybase/batch.py
aiohappybase/connection.py
aiohappybase/pool.py
aiohappybase/table.py
aiohappybase/sync/__init__.py
aiohappybase/sync/_util.py
aiohappybase/sync/batch.py
aiohappybase/sync/batch.pyi
aiohappybase/sync/connection.py
aiohappybase/sync/connection.pyi
aiohappybase/sync/pool.py
aiohappybase/sync/pool.pyi
aiohappybase/sync/table.py
aiohappybase/sync/table.pyi
aiohappybase-1.4.0.dist-info/LICENSE.rst
aiohappybase-1.4.0.dist-info/METADATA
aiohappybase-1.4.0.dist-info/WHEEL
aiohappybase-1.4.0.dist-info/top_level.txt
aiohappybase-1.4.0.dist-info/RECORD
