Metadata-Version: 1.1
Name: aiohappybase
Version: 1.4.0
Summary: Asyncio fork of HappyBase
Home-page: https://github.com/python-happybase/aiohappybase
Author: Roger Aiudi
Author-email: aiudirog@gmail.com
License: MIT
Keywords: hbase,thrift,async,asyncio,happybase
Platform: UNKNOWN
Classifier: Development Status :: 5 - Production/Stable
Classifier: Intended Audience :: Developers
Classifier: License :: OSI Approved :: MIT License
Classifier: Programming Language :: Python :: 3.6
Classifier: Programming Language :: Python :: 3.7
Classifier: Programming Language :: Python :: 3.8
Classifier: Programming Language :: Python :: 3.9
Classifier: Topic :: Database
Classifier: Topic :: Software Development :: Libraries :: Python Modules
